{
  "last_run": "2026-05-29T11:45:31.616051+00:00",
  "protocols": {
    "OnRe": {
      "tvl": 188963609.65349,
      "price": null,
      "status": "🟢"
    },
    "Altura": {
      "tvl": 25785022.45424,
      "price": null,
      "status": "🟢"
    },
    "Unitas": {
      "tvl": 64908799.15056,
      "price": null,
      "status": "🟡"
    },
    "Hylo": {
      "tvl": 37115291,
      "price": null,
      "status": "🟢"
    },
    "Paxos Global Dollar": {
      "tvl": null,
      "price": 0.999788,
      "status": "🟢"
    },
    "Ethena": {
      "tvl": 5482291038.6912,
      "price": 0.998663,
      "status": "🟢"
    },
    "Apyx": {
      "tvl": null,
      "price": null,
      "status": "🟢"
    }
  }
}